utils_ai/__init__.py
utils_ai/apps/ChatApp.py
utils_ai/apps/__init__.py
utils_ai/core/ChatRole.py
utils_ai/core/Message.py
utils_ai/core/__init__.py
utils_ai/generic_ai/GenericAI.py
utils_ai/generic_ai/GenericAIImage.py
utils_ai/generic_ai/GenericAIText.py
utils_ai/generic_ai/__init__.py
utils_ai/providers/MistralAIProvider.py
utils_ai/providers/OpenAIProvider.py
utils_ai/providers/ProviderFactory.py
utils_ai/providers/__init__.py
utils_ai_nuuuwan-1.0.5.dist-info/LICENSE
utils_ai_nuuuwan-1.0.5.dist-info/METADATA
utils_ai_nuuuwan-1.0.5.dist-info/WHEEL
utils_ai_nuuuwan-1.0.5.dist-info/top_level.txt
utils_ai_nuuuwan-1.0.5.dist-info/RECORD
