Metadata-Version: 2.1
Name: utils_ai-nuuuwan
Version: 1.0.5
Summary: Utilities with AI support
Home-page: https://github.com/nuuuwan/utils_ai
Author: Nuwan I. Senaratna
Author-email: nuuuwan@gmail.com
Project-URL: Bug Tracker, https://github.com/nuuuwan/utils_ai/issues
Classifier: Programming Language :: Python :: 3
Classifier: License :: OSI Approved :: MIT License
Classifier: Operating System :: OS Independent
Requires-Python: >=3.10
License-File: LICENSE
Requires-Dist: utils-base-nuuuwan
Requires-Dist: utils-www-nuuuwan
Requires-Dist: openai
Requires-Dist: mistralai
